legendyoutube.py
legendyoutube-0.0.1.dist-info/WHEEL
legendyoutube-0.0.1.dist-info/METADATA
legendyoutube-0.0.1.dist-info/RECORD
